labonneboite_datamodel/__init__.py
labonneboite_datamodel/base.py
labonneboite_datamodel/naf.py
labonneboite_datamodel/office.py
labonneboite_datamodel/rome.py
labonneboite_datamodel/sent_emails.py
labonneboite_datamodel/tests/__init__.py
labonneboite_datamodel/tests/data/test.csv
labonneboite_datamodel/tests/test_base.py
labonneboite_datamodel/tests/test_job.py
labonneboite_datamodel/tests/test_office.py
labonneboite_datamodel/tests/test_office_metadata.py
labonneboite_datamodel/tests/test_rome.py
labonneboite_datamodel/tests/test_sent_emails.py
labonneboite_datamodel/validators.py
labonneboite_datamodel-2.7.0.dist-info/METADATA
labonneboite_datamodel-2.7.0.dist-info/WHEEL
labonneboite_datamodel-2.7.0.dist-info/RECORD
