Metadata-Version: 2.4
Name: labonneboite-datamodel
Version: 2.7.0
Summary: Datamodel for labonneboite
License: MIT
Author: La Bonne Boite
Author-email: labonneboite@pole-emploi.fr
Requires-Python: >=3.11,<4.0
Classifier: License :: OSI Approved :: MIT License
Classifier: Programming Language :: Python :: 3
Classifier: Programming Language :: Python :: 3.11
Classifier: Programming Language :: Python :: 3.12
Classifier: Programming Language :: Python :: 3.13
Classifier: Programming Language :: Python :: 3.14
Requires-Dist: email-validator (>=2.2.0,<3.0.0)
Requires-Dist: pydantic (>=2.5.3,<3.0.0)
Requires-Dist: pymysql (>=1.0.2,<2.0.0)
Requires-Dist: sqlmodel (>=0.0.22,<0.0.23)
